byteair/__init__.py
byteair/client.py
byteair/url.py
byteair/protocol/__init__.py
byteair/protocol/volcengine_byteair_pb2.py
common/__init__.py
common/client.py
common/url.py
common/protocol/__init__.py
common/protocol/volcengine_common_pb2.py
core/__init__.py
core/constant.py
core/context.py
core/exception.py
core/http_caller.py
core/metrics_helper.py
core/option.py
core/options.py
core/time_helper.py
core/url_center.py
core/metrics/__init__.py
core/metrics/constant.py
core/metrics/helper.py
core/metrics/metrics_collector.py
core/metrics/metrics_example.py
core/metrics/metrics_option.py
core/metrics/sample.py
core/metrics/volcengine_rec_sdk_metrics_pb2.py
volcauth/__init__.py
volcauth/exceptions.py
volcauth/volcauth.py
volcauth/volcsigningkey.py
volcengine_sdk_rec-1.3.4.dist-info/LICENSE
volcengine_sdk_rec-1.3.4.dist-info/METADATA
volcengine_sdk_rec-1.3.4.dist-info/WHEEL
volcengine_sdk_rec-1.3.4.dist-info/top_level.txt
volcengine_sdk_rec-1.3.4.dist-info/RECORD
