Metadata-Version: 2.1
Name: volcengine_sdk_rec
Version: 1.3.4
Summary: SDK for volcengine
Home-page: https://github.com/volcengine/volcengine-sdk-python-rec
Author: Lin Gan
Author-email: ganlin.coder@bytedance.com
License: Apache 2.0
Project-URL: Source, https://github.com/volcengine/volcengine-sdk-python-rec
Classifier: Development Status :: 5 - Production/Stable
Classifier: Intended Audience :: Developers
Classifier: Natural Language :: English
Classifier: License :: OSI Approved :: Apache Software License
Classifier: Programming Language :: Python
Classifier: Programming Language :: Python :: 3
Classifier: Programming Language :: Python :: 3.5
Classifier: Programming Language :: Python :: 3.6
Classifier: Programming Language :: Python :: 3.7
Classifier: Programming Language :: Python :: 3.8
Classifier: Programming Language :: Python :: 3.9
Classifier: Programming Language :: Python :: 3.10
Classifier: Programming Language :: Python :: Implementation :: CPython
Classifier: Programming Language :: Python :: Implementation :: PyPy
Requires-Python: >=3
License-File: LICENSE
Requires-Dist: protobuf ==3.20.1
Requires-Dist: requests
Requires-Dist: six
Requires-Dist: numpy
